{
  "version": "1.0.0",
  "purpose": "Defines voice and audio direction for generated voiceovers and audio assets.",
  "voice_style": {
    "tone": "confident, premium, warm, clear, trustworthy",
    "pace": "medium, energetic but not rushed",
    "delivery": "natural commercial voice, not robotic, not exaggerated",
    "language": "German-market ready, clear pronunciation, concise wording"
  },
  "audio_rules": {
    "hook": "first sentence must create attention quickly",
    "clarity": "avoid long sentences and unclear claims",
    "timing": "match narration to scene beats",
    "cta": "end with a clear but not aggressive call to action"
  },
  "avoid": [
    "medical promises",
    "overhyped claims",
    "too many benefits in one sentence",
    "robotic script structure",
    "unverified certifications"
  ]
}
