{
  "generated_at": "2026-06-20T23:57:21.902Z",
  "closedTargets": [
    [
      "workflows.js",
      "Workflows"
    ],
    [
      "publishing.js",
      "Publishing"
    ],
    [
      "library.js",
      "Library"
    ],
    [
      "ai-command.js",
      "AI Command"
    ],
    [
      "ai-command/tool-dock.js",
      "AI Command Tool Dock"
    ],
    [
      "integrations.js",
      "Integrations"
    ],
    [
      "settings.js",
      "Settings"
    ],
    [
      "media-studio-workspace.js",
      "Media Studio Workspace"
    ],
    [
      "governance.js",
      "Governance"
    ],
    [
      "operations-centers.js",
      "Operations Centers"
    ],
    [
      "content-studio-workspace.js",
      "Content Studio Workspace"
    ]
  ],
  "nextCandidate": {
    "rel": "public/control-center/pages/campaign-studio.js",
    "pageRel": "campaign-studio.js",
    "closed": false,
    "closedLabel": "",
    "lines": 2023,
    "innerHtml": 1,
    "events": 12,
    "apiSignals": 90,
    "authorityWords": 131,
    "confirmation": 0,
    "storage": 0,
    "escapeEvidence": 165,
    "score": 254.2,
    "priority": "P0"
  },
  "rows": [
    {
      "rel": "public/control-center/pages/ads-manager.js",
      "pageRel": "ads-manager.js",
      "closed": false,
      "closedLabel": "",
      "lines": 624,
      "innerHtml": 1,
      "events": 4,
      "apiSignals": 8,
      "authorityWords": 10,
      "confirmation": 0,
      "storage": 0,
      "escapeEvidence": 62,
      "score": 30.3,
      "priority": "P2"
    },
    {
      "rel": "public/control-center/pages/ai-command.js",
      "pageRel": "ai-command.js",
      "closed": true,
      "closedLabel": "AI Command",
      "lines": 6183,
      "innerHtml": 1,
      "events": 34,
      "apiSignals": 488,
      "authorityWords": 893,
      "confirmation": 0,
      "storage": 6,
      "escapeEvidence": 505,
      "score": 1381.5,
      "priority": "P0"
    },
    {
      "rel": "public/control-center/pages/ai-command/tool-dock.js",
      "pageRel": "ai-command/tool-dock.js",
      "closed": true,
      "closedLabel": "AI Command Tool Dock",
      "lines": 1867,
      "innerHtml": 4,
      "events": 8,
      "apiSignals": 90,
      "authorityWords": 145,
      "confirmation": 0,
      "storage": 0,
      "escapeEvidence": 20,
      "score": 266.2,
      "priority": "P0"
    },
    {
      "rel": "public/control-center/pages/campaign-studio.js",
      "pageRel": "campaign-studio.js",
      "closed": false,
      "closedLabel": "",
      "lines": 2023,
      "innerHtml": 1,
      "events": 12,
      "apiSignals": 90,
      "authorityWords": 131,
      "confirmation": 0,
      "storage": 0,
      "escapeEvidence": 165,
      "score": 254.2,
      "priority": "P0"
    },
    {
      "rel": "public/control-center/pages/content-studio-workspace.js",
      "pageRel": "content-studio-workspace.js",
      "closed": true,
      "closedLabel": "Content Studio Workspace",
      "lines": 2461,
      "innerHtml": 1,
      "events": 14,
      "apiSignals": 184,
      "authorityWords": 406,
      "confirmation": 2,
      "storage": 4,
      "escapeEvidence": 180,
      "score": 546.8,
      "priority": "P0"
    },
    {
      "rel": "public/control-center/pages/customer-center.js",
      "pageRel": "customer-center.js",
      "closed": false,
      "closedLabel": "",
      "lines": 470,
      "innerHtml": 0,
      "events": 1,
      "apiSignals": 28,
      "authorityWords": 73,
      "confirmation": 0,
      "storage": 0,
      "escapeEvidence": 28,
      "score": 86.3,
      "priority": "P0"
    },
    {
      "rel": "public/control-center/pages/governance.js",
      "pageRel": "governance.js",
      "closed": true,
      "closedLabel": "Governance",
      "lines": 1521,
      "innerHtml": 2,
      "events": 9,
      "apiSignals": 256,
      "authorityWords": 738,
      "confirmation": 6,
      "storage": 0,
      "escapeEvidence": 209,
      "score": 784.4,
      "priority": "P0"
    },
    {
      "rel": "public/control-center/pages/home.js",
      "pageRel": "home.js",
      "closed": false,
      "closedLabel": "",
      "lines": 1164,
      "innerHtml": 1,
      "events": 14,
      "apiSignals": 73,
      "authorityWords": 104,
      "confirmation": 0,
      "storage": 0,
      "escapeEvidence": 83,
      "score": 211.6,
      "priority": "P0"
    },
    {
      "rel": "public/control-center/pages/home/render-sections.js",
      "pageRel": "home/render-sections.js",
      "closed": false,
      "closedLabel": "",
      "lines": 156,
      "innerHtml": 0,
      "events": 0,
      "apiSignals": 2,
      "authorityWords": 7,
      "confirmation": 0,
      "storage": 0,
      "escapeEvidence": 34,
      "score": 8.7,
      "priority": "P3"
    },
    {
      "rel": "public/control-center/pages/insights.js",
      "pageRel": "insights.js",
      "closed": false,
      "closedLabel": "",
      "lines": 1520,
      "innerHtml": 1,
      "events": 4,
      "apiSignals": 26,
      "authorityWords": 38,
      "confirmation": 0,
      "storage": 0,
      "escapeEvidence": 115,
      "score": 77.7,
      "priority": "P0"
    },
    {
      "rel": "public/control-center/pages/integrations.js",
      "pageRel": "integrations.js",
      "closed": true,
      "closedLabel": "Integrations",
      "lines": 1992,
      "innerHtml": 1,
      "events": 13,
      "apiSignals": 83,
      "authorityWords": 256,
      "confirmation": 2,
      "storage": 0,
      "escapeEvidence": 69,
      "score": 273.4,
      "priority": "P0"
    },
    {
      "rel": "public/control-center/pages/integrations/builders.js",
      "pageRel": "integrations/builders.js",
      "closed": false,
      "closedLabel": "",
      "lines": 818,
      "innerHtml": 0,
      "events": 0,
      "apiSignals": 8,
      "authorityWords": 56,
      "confirmation": 0,
      "storage": 0,
      "escapeEvidence": 17,
      "score": 37.6,
      "priority": "P2"
    },
    {
      "rel": "public/control-center/pages/integrations/cards.js",
      "pageRel": "integrations/cards.js",
      "closed": false,
      "closedLabel": "",
      "lines": 414,
      "innerHtml": 0,
      "events": 0,
      "apiSignals": 1,
      "authorityWords": 30,
      "confirmation": 0,
      "storage": 0,
      "escapeEvidence": 8,
      "score": 16,
      "priority": "P3"
    },
    {
      "rel": "public/control-center/pages/integrations/diagnostics.js",
      "pageRel": "integrations/diagnostics.js",
      "closed": false,
      "closedLabel": "",
      "lines": 159,
      "innerHtml": 0,
      "events": 0,
      "apiSignals": 0,
      "authorityWords": 13,
      "confirmation": 0,
      "storage": 0,
      "escapeEvidence": 6,
      "score": 9.3,
      "priority": "P3"
    },
    {
      "rel": "public/control-center/pages/integrations/drawer.js",
      "pageRel": "integrations/drawer.js",
      "closed": false,
      "closedLabel": "",
      "lines": 439,
      "innerHtml": 0,
      "events": 0,
      "apiSignals": 0,
      "authorityWords": 19,
      "confirmation": 0,
      "storage": 0,
      "escapeEvidence": 6,
      "score": 11,
      "priority": "P3"
    },
    {
      "rel": "public/control-center/pages/integrations/layout.js",
      "pageRel": "integrations/layout.js",
      "closed": false,
      "closedLabel": "",
      "lines": 187,
      "innerHtml": 0,
      "events": 0,
      "apiSignals": 0,
      "authorityWords": 6,
      "confirmation": 0,
      "storage": 0,
      "escapeEvidence": 3,
      "score": 7.7,
      "priority": "P3"
    },
    {
      "rel": "public/control-center/pages/integrations/render.js",
      "pageRel": "integrations/render.js",
      "closed": false,
      "closedLabel": "",
      "lines": 206,
      "innerHtml": 0,
      "events": 0,
      "apiSignals": 0,
      "authorityWords": 3,
      "confirmation": 0,
      "storage": 0,
      "escapeEvidence": 3,
      "score": 6.9,
      "priority": "P3"
    },
    {
      "rel": "public/control-center/pages/integrations/state.js",
      "pageRel": "integrations/state.js",
      "closed": false,
      "closedLabel": "",
      "lines": 93,
      "innerHtml": 0,
      "events": 0,
      "apiSignals": 0,
      "authorityWords": 2,
      "confirmation": 0,
      "storage": 0,
      "escapeEvidence": 1,
      "score": 6.8,
      "priority": "P3"
    },
    {
      "rel": "public/control-center/pages/integrations/utils.js",
      "pageRel": "integrations/utils.js",
      "closed": false,
      "closedLabel": "",
      "lines": 114,
      "innerHtml": 0,
      "events": 0,
      "apiSignals": 0,
      "authorityWords": 4,
      "confirmation": 0,
      "storage": 0,
      "escapeEvidence": 2,
      "score": 7.3,
      "priority": "P3"
    },
    {
      "rel": "public/control-center/pages/library.js",
      "pageRel": "library.js",
      "closed": true,
      "closedLabel": "Library",
      "lines": 3563,
      "innerHtml": 26,
      "events": 58,
      "apiSignals": 79,
      "authorityWords": 187,
      "confirmation": 4,
      "storage": 1,
      "escapeEvidence": 224,
      "score": 387.2,
      "priority": "P0"
    },
    {
      "rel": "public/control-center/pages/library/action-panel.js",
      "pageRel": "library/action-panel.js",
      "closed": false,
      "closedLabel": "",
      "lines": 150,
      "innerHtml": 0,
      "events": 0,
      "apiSignals": 5,
      "authorityWords": 16,
      "confirmation": 0,
      "storage": 0,
      "escapeEvidence": 0,
      "score": 21.9,
      "priority": "P2"
    },
    {
      "rel": "public/control-center/pages/library/ai-panel.js",
      "pageRel": "library/ai-panel.js",
      "closed": false,
      "closedLabel": "",
      "lines": 123,
      "innerHtml": 0,
      "events": 0,
      "apiSignals": 1,
      "authorityWords": 3,
      "confirmation": 0,
      "storage": 0,
      "escapeEvidence": 0,
      "score": 9.4,
      "priority": "P3"
    },
    {
      "rel": "public/control-center/pages/library/catalog-readiness.js",
      "pageRel": "library/catalog-readiness.js",
      "closed": false,
      "closedLabel": "",
      "lines": 65,
      "innerHtml": 0,
      "events": 0,
      "apiSignals": 0,
      "authorityWords": 1,
      "confirmation": 0,
      "storage": 0,
      "escapeEvidence": 0,
      "score": 6.7,
      "priority": "P3"
    },
    {
      "rel": "public/control-center/pages/library/command-router.js",
      "pageRel": "library/command-router.js",
      "closed": false,
      "closedLabel": "",
      "lines": 64,
      "innerHtml": 0,
      "events": 0,
      "apiSignals": 3,
      "authorityWords": 9,
      "confirmation": 0,
      "storage": 0,
      "escapeEvidence": 0,
      "score": 15.5,
      "priority": "P3"
    },
    {
      "rel": "public/control-center/pages/library/listener-lifecycle.js",
      "pageRel": "library/listener-lifecycle.js",
      "closed": false,
      "closedLabel": "",
      "lines": 63,
      "innerHtml": 0,
      "events": 1,
      "apiSignals": 0,
      "authorityWords": 3,
      "confirmation": 0,
      "storage": 0,
      "escapeEvidence": 0,
      "score": 8.4,
      "priority": "P3"
    },
    {
      "rel": "public/control-center/pages/library/projection-adapter.js",
      "pageRel": "library/projection-adapter.js",
      "closed": false,
      "closedLabel": "",
      "lines": 21,
      "innerHtml": 0,
      "events": 0,
      "apiSignals": 0,
      "authorityWords": 2,
      "confirmation": 0,
      "storage": 0,
      "escapeEvidence": 0,
      "score": 7,
      "priority": "P3"
    },
    {
      "rel": "public/control-center/pages/library/session-store.js",
      "pageRel": "library/session-store.js",
      "closed": false,
      "closedLabel": "",
      "lines": 45,
      "innerHtml": 0,
      "events": 0,
      "apiSignals": 0,
      "authorityWords": 3,
      "confirmation": 0,
      "storage": 0,
      "escapeEvidence": 0,
      "score": 7.2,
      "priority": "P3"
    },
    {
      "rel": "public/control-center/pages/media-studio-workspace.js",
      "pageRel": "media-studio-workspace.js",
      "closed": true,
      "closedLabel": "Media Studio Workspace",
      "lines": 3753,
      "innerHtml": 1,
      "events": 29,
      "apiSignals": 338,
      "authorityWords": 737,
      "confirmation": 1,
      "storage": 4,
      "escapeEvidence": 280,
      "score": 997.1,
      "priority": "P0"
    },
    {
      "rel": "public/control-center/pages/operations-centers.js",
      "pageRel": "operations-centers.js",
      "closed": true,
      "closedLabel": "Operations Centers",
      "lines": 2268,
      "innerHtml": 5,
      "events": 26,
      "apiSignals": 274,
      "authorityWords": 523,
      "confirmation": 1,
      "storage": 0,
      "escapeEvidence": 268,
      "score": 798.7,
      "priority": "P0"
    },
    {
      "rel": "public/control-center/pages/publishing.js",
      "pageRel": "publishing.js",
      "closed": true,
      "closedLabel": "Publishing",
      "lines": 2060,
      "innerHtml": 1,
      "events": 20,
      "apiSignals": 589,
      "authorityWords": 721,
      "confirmation": 7,
      "storage": 2,
      "escapeEvidence": 136,
      "score": 1525.2,
      "priority": "P0"
    },
    {
      "rel": "public/control-center/pages/publishing/publishing-payloads.js",
      "pageRel": "publishing/publishing-payloads.js",
      "closed": false,
      "closedLabel": "",
      "lines": 119,
      "innerHtml": 0,
      "events": 0,
      "apiSignals": 17,
      "authorityWords": 32,
      "confirmation": 0,
      "storage": 0,
      "escapeEvidence": 6,
      "score": 52,
      "priority": "P1"
    },
    {
      "rel": "public/control-center/pages/research.js",
      "pageRel": "research.js",
      "closed": false,
      "closedLabel": "",
      "lines": 1613,
      "innerHtml": 1,
      "events": 11,
      "apiSignals": 11,
      "authorityWords": 32,
      "confirmation": 0,
      "storage": 0,
      "escapeEvidence": 101,
      "score": 51.5,
      "priority": "P1"
    },
    {
      "rel": "public/control-center/pages/settings.js",
      "pageRel": "settings.js",
      "closed": true,
      "closedLabel": "Settings",
      "lines": 2057,
      "innerHtml": 5,
      "events": 4,
      "apiSignals": 207,
      "authorityWords": 424,
      "confirmation": 1,
      "storage": 0,
      "escapeEvidence": 122,
      "score": 597.2,
      "priority": "P0"
    },
    {
      "rel": "public/control-center/pages/setup.js",
      "pageRel": "setup.js",
      "closed": false,
      "closedLabel": "",
      "lines": 1787,
      "innerHtml": 3,
      "events": 25,
      "apiSignals": 16,
      "authorityWords": 35,
      "confirmation": 0,
      "storage": 6,
      "escapeEvidence": 172,
      "score": 99.1,
      "priority": "P0"
    },
    {
      "rel": "public/control-center/pages/workflows.js",
      "pageRel": "workflows.js",
      "closed": true,
      "closedLabel": "Workflows",
      "lines": 2395,
      "innerHtml": 1,
      "events": 40,
      "apiSignals": 132,
      "authorityWords": 443,
      "confirmation": 8,
      "storage": 2,
      "escapeEvidence": 162,
      "score": 465.1,
      "priority": "P0"
    }
  ]
}